subscribe_check_guard/__init__.py
subscribe_check_guard/core.py
subscribe_check_guard-0.1.0.dist-info/licenses/LICENSE
subscribe_check_guard-0.1.0.dist-info/METADATA
subscribe_check_guard-0.1.0.dist-info/WHEEL
subscribe_check_guard-0.1.0.dist-info/top_level.txt
subscribe_check_guard-0.1.0.dist-info/RECORD
