Metadata-Version: 2.4
Name: subscribe_check_guard
Version: 0.1.0
Summary: Лёгкая библиотека для aiogram: проверка подписки на Telegram-каналы и управление администраторами бота. Простая настройка и интеграция.
Author-email: MuhammadAli Astanaqulov <im.ali@astanaqulov.ru>
License: MIT
Project-URL: Homepage, https://github.com/k1ng-ali/subscribe_check_guard
Project-URL: Repository, https://github.com/k1ng-ali/subscribe_check_guard
Requires-Python: >=3.10
License-File: LICENSE
Requires-Dist: aiogram>=3.4
Dynamic: license-file
